nicehash2mqtt.py
nicehash2mqtt-0.0.17.dist-info/METADATA
nicehash2mqtt-0.0.17.dist-info/WHEEL
nicehash2mqtt-0.0.17.dist-info/entry_points.txt
nicehash2mqtt-0.0.17.dist-info/top_level.txt
nicehash2mqtt-0.0.17.dist-info/RECORD
