Metadata-Version: 2.1
Name: nicehash2mqtt
Version: 0.0.17
Summary: Bridge between nicehash and mqtt
Home-page: https://github.com/nslythe/nicehash2mqtt
Author: Nicolas Slythe
Author-email: nicehash2mqtt@slythe.net
License: UNKNOWN
Project-URL: Bug Tracker, https://github.com/nslythe/nicehash2mqtt/issues
Platform: UNKNOWN
Classifier: Programming Language :: Python :: 3
Classifier: License :: OSI Approved :: MIT License
Classifier: Operating System :: OS Independent
Requires-Python: >=3.6
Requires-Dist: pynicehash
Requires-Dist: paho-mqtt
